millwheel/__init__.py
millwheel/scheduler.py
millwheel/utils.py
millwheel-0.1.2.dist-info/AUTHORS.rst
millwheel-0.1.2.dist-info/LICENSE
millwheel-0.1.2.dist-info/METADATA
millwheel-0.1.2.dist-info/WHEEL
millwheel-0.1.2.dist-info/top_level.txt
millwheel-0.1.2.dist-info/RECORD
